LiaoXuefengJavaJiaocheng/README.md
LiaoXuefengJavaJiaocheng/__init__.py
LiaoXuefengJavaJiaocheng/__main__.py
LiaoXuefengJavaJiaocheng/file.epub
LiaoXuefengJavaJiaocheng/index.html
LiaoXuefengJavaJiaocheng/css/__init__.py
LiaoXuefengJavaJiaocheng/css/annotations.css
LiaoXuefengJavaJiaocheng/css/main.css
LiaoXuefengJavaJiaocheng/css/normalize.css
LiaoXuefengJavaJiaocheng/css/popup.css
LiaoXuefengJavaJiaocheng/font/__init__.py
LiaoXuefengJavaJiaocheng/font/fontello.eot
LiaoXuefengJavaJiaocheng/font/fontello.svg
LiaoXuefengJavaJiaocheng/font/fontello.ttf
LiaoXuefengJavaJiaocheng/font/fontello.woff
LiaoXuefengJavaJiaocheng/img/__init__.py
LiaoXuefengJavaJiaocheng/img/annotator-glyph-sprite.png
LiaoXuefengJavaJiaocheng/img/annotator-icon-sprite.png
LiaoXuefengJavaJiaocheng/img/apple-touch-icon.png
LiaoXuefengJavaJiaocheng/img/cancelfullscreen.png
LiaoXuefengJavaJiaocheng/img/close.png
LiaoXuefengJavaJiaocheng/img/fullscreen.png
LiaoXuefengJavaJiaocheng/img/loader.gif
LiaoXuefengJavaJiaocheng/img/menu-icon.png
LiaoXuefengJavaJiaocheng/img/save.png
LiaoXuefengJavaJiaocheng/img/saved.png
LiaoXuefengJavaJiaocheng/img/settings-s.png
LiaoXuefengJavaJiaocheng/img/settings.png
LiaoXuefengJavaJiaocheng/img/star.png
LiaoXuefengJavaJiaocheng/js/__init__.py
LiaoXuefengJavaJiaocheng/js/epub.js
LiaoXuefengJavaJiaocheng/js/epub.min.js
LiaoXuefengJavaJiaocheng/js/epub.min.map
LiaoXuefengJavaJiaocheng/js/hooks.min.js
LiaoXuefengJavaJiaocheng/js/hooks.min.map
LiaoXuefengJavaJiaocheng/js/reader.js
LiaoXuefengJavaJiaocheng/js/reader.js.map
LiaoXuefengJavaJiaocheng/js/reader.min.js
LiaoXuefengJavaJiaocheng/js/reader.min.map
LiaoXuefengJavaJiaocheng/js/hooks/__init__.py
LiaoXuefengJavaJiaocheng/js/hooks/extensions/__init__.py
LiaoXuefengJavaJiaocheng/js/hooks/extensions/highlight.js
LiaoXuefengJavaJiaocheng/js/libs/__init__.py
LiaoXuefengJavaJiaocheng/js/libs/jquery.min.js
LiaoXuefengJavaJiaocheng/js/libs/localforage.min.js
LiaoXuefengJavaJiaocheng/js/libs/screenfull.js
liao_xuefeng_java_jiaocheng-2024.3.5.0.dist-info/METADATA
liao_xuefeng_java_jiaocheng-2024.3.5.0.dist-info/WHEEL
liao_xuefeng_java_jiaocheng-2024.3.5.0.dist-info/entry_points.txt
liao_xuefeng_java_jiaocheng-2024.3.5.0.dist-info/top_level.txt
liao_xuefeng_java_jiaocheng-2024.3.5.0.dist-info/RECORD
